{"stats":{"minecraft:custom":{"minecraft:jump":254,"minecraft:open_chest":2,"minecraft:time_since_rest":24040,"minecraft:damage_taken":460,"minecraft:leave_game":2,"minecraft:crouch_one_cm":120,"minecraft:time_since_death":24019,"minecraft:play_time":28449,"minecraft:sprint_one_cm":27480,"minecraft:walk_one_cm":7998,"minecraft:walk_on_water_one_cm":3085,"minecraft:deaths":1,"minecraft:trigger_trapped_chest":2,"minecraft:sneak_time":274,"minecraft:total_world_time":34432,"minecraft:climb_one_cm":1332,"minecraft:walk_under_water_one_cm":679,"minecraft:swim_one_cm":3099,"minecraft:fall_one_cm":12302,"minecraft:drop":1,"minecraft:fly_one_cm":118530},"minecraft:dropped":{"minecraft:torch":1}},"DataVersion":3465}